[
    {
        "id": 1,
        "username": "刘明霞",
        "password": "123456",
        "payPassword":""
    }
    ,
    {
        "id": 2,
        "username": "曾东杰",
        "password": "123456",
        "payPassword":""
    }
    ,
    {
        "id": 3,
        "username": "娄梦梦",
        "password": "123456",
        "payPassword":""
    }
    ,
    {
        "id": 4,
        "username": "尚帅",
        "password": "123456",
        "payPassword":""
    },
    {
        "id": 5,
        "username": "杨洋",
        "password": "123456",
        "payPassword":""
    }
  
]